well_architected_stacks/__init__.py
well_architected_stacks/api_lambda_dynamodb.py
well_architected_stacks/api_lambda_dynamodb_eventbridge_lambda.py
well_architected_stacks/api_lambda_eventbridge_lambda.py
well_architected_stacks/api_lambda_rds.py
well_architected_stacks/api_lambda_sqs_lambda_dynamodb.py
well_architected_stacks/api_step_functions.py
well_architected_stacks/lambda_power_tuner.py
well_architected_stacks/rest_api_dynamodb.py
well_architected_stacks/rest_api_sns.py
well_architected_stacks/rest_api_sns_lambda_eventbridge_lambda.py
well_architected_stacks/rest_api_sns_sqs_lambda.py
well_architected_stacks/s3_sqs_lambda_ecs_eventbridge_lambda_dynamodb.py
well_architected_stacks/saga_step_function.py
well_architected_stacks/sns_lambda.py
well_architected_stacks/sns_lambda_dynamodb.py
well_architected_stacks/sns_lambda_sns.py
well_architected_stacks/sns_topic.py
well_architected_stacks/sqs_lambda_sqs.py
well_architected_stacks/waf_rest_api_lambda_dynamodb.py
well_architected_stacks/well_architected_app.py
well_architected_stacks/well_architected_stack.py
well_architected_stacks/lambda_trilogy/__init__.py
well_architected_stacks/lambda_trilogy/lambda_lith.py
well_architected_stacks/lambda_trilogy/lambda_trilogy.py
well_architected_stacks/simple_graphql_service/__init__.py
well_architected_stacks/simple_graphql_service/simple_graphql_service.py
well_architected_stacks-0.0.17.dist-info/LICENSE
well_architected_stacks-0.0.17.dist-info/METADATA
well_architected_stacks-0.0.17.dist-info/WHEEL
well_architected_stacks-0.0.17.dist-info/top_level.txt
well_architected_stacks-0.0.17.dist-info/RECORD
